[ 
 	{ 
		 "ALL": [
		{
			 "id": 0,
			 "entropy": 1.0
		},
		{
			 "id": 1,
			 "entropy": 0.9817340444471978
		},
		{
			 "id": 2,
			 "entropy": 0.7366390217007458
		},
		{
			 "id": 3,
			 "entropy": 0.8106549095769529
		},
		{
			 "id": 4,
			 "entropy": 0.5899339809605081
		},
		{
			 "id": 5,
			 "entropy": 0.7655562159384075
		},
		{
			 "id": 6,
			 "entropy": 0.0
		},
		{
			 "id": 7,
			 "entropy": 0.20394550166332467
		},
		{
			 "id": 8,
			 "entropy": 0.46633941858872596
		},
		{
			 "id": 9,
			 "entropy": 0.5572304624334938
		},
		{
			 "id": 10,
			 "entropy": 0.5395548858758763
		},
		{
			 "id": 11,
			 "entropy": 0.39194058974664353
		},
		{
			 "id": 12,
			 "entropy": 0.6315588939429996
		},
		{
			 "id": 13,
			 "entropy": 0.6838555557069927
		},
		{
			 "id": 14,
			 "entropy": 0.38749223176289227
		},
		{
			 "id": 15,
			 "entropy": 0.35100447840788124
		},
		{
			 "id": 16,
			 "entropy": 0.5935745618312279
		},
		{
			 "id": 17,
			 "entropy": 0.6006120127802443
		},
		{
			 "id": 18,
			 "entropy": 0.5336378950360998
		},
		{
			 "id": 19,
			 "entropy": 0.34681709302681957
		},
		{
			 "id": 20,
			 "entropy": 0.4366527167948422
		},
		{
			 "id": 21,
			 "entropy": 0.40577562865834305
		},
		{
			 "id": 22,
			 "entropy": 0.42160369924404933
		},
		{
			 "id": 23,
			 "entropy": 0.5086625724069446
		},
		{
			 "id": 24,
			 "entropy": 0.1454083355138574
		},
		{
			 "id": 25,
			 "entropy": 0.4390872392215099
		},
		{
			 "id": 26,
			 "entropy": 0.09431696094450048
		},
		{
			 "id": 27,
			 "entropy": 0.5536405073442615
		},
		{
			 "id": 28,
			 "entropy": 0.38911083240638417
		},
		{
			 "id": 29,
			 "entropy": 0.591547732592247
		},
		{
			 "id": 30,
			 "entropy": 0.6121570144914104
		},
		{
			 "id": 31,
			 "entropy": 0.3706726705078441
		},
		{
			 "id": 32,
			 "entropy": 0.14797659031559937
		},
		{
			 "id": 33,
			 "entropy": 0.0365131607667001
		},
		{
			 "id": 34,
			 "entropy": 0.42138083765244055
		},
		{
			 "id": 35,
			 "entropy": 0.048488184075633656
		},
		{
			 "id": 36,
			 "entropy": 0.1671155177313854
		}
		 ]
	}]