[ 
 	{ 
		 "ALL": [
		{
			 "id": 0,
			 "entropy": 0.7212921496424352
		},
		{
			 "id": 1,
			 "entropy": 0.7212921496424352
		},
		{
			 "id": 2,
			 "entropy": 0.23214090443226051
		},
		{
			 "id": 3,
			 "entropy": 0.42381166122865455
		},
		{
			 "id": 4,
			 "entropy": 0.6725933206594222
		},
		{
			 "id": 5,
			 "entropy": 0.8713849082027292
		},
		{
			 "id": 6,
			 "entropy": 0.2514713041818315
		},
		{
			 "id": 7,
			 "entropy": 0.2626959807786626
		},
		{
			 "id": 8,
			 "entropy": 0.3794289340264548
		},
		{
			 "id": 9,
			 "entropy": 0.24624261009091983
		},
		{
			 "id": 10,
			 "entropy": 0.7576871165502151
		},
		{
			 "id": 11,
			 "entropy": 0.5912455104165489
		},
		{
			 "id": 12,
			 "entropy": 0.2735136802607301
		},
		{
			 "id": 13,
			 "entropy": 0.40012417116635585
		},
		{
			 "id": 14,
			 "entropy": 0.41631122034518236
		},
		{
			 "id": 15,
			 "entropy": 0.06808415364719161
		},
		{
			 "id": 16,
			 "entropy": 0.3254442532702086
		},
		{
			 "id": 17,
			 "entropy": 0.33536872815218255
		},
		{
			 "id": 18,
			 "entropy": 0.32111421009729
		},
		{
			 "id": 19,
			 "entropy": 0.12718134993030034
		},
		{
			 "id": 20,
			 "entropy": 0.06786890230586247
		},
		{
			 "id": 21,
			 "entropy": 0.2797441222219526
		},
		{
			 "id": 22,
			 "entropy": 0.42082544726866455
		},
		{
			 "id": 23,
			 "entropy": 0.3887973941265213
		},
		{
			 "id": 24,
			 "entropy": 0.30309104327734326
		},
		{
			 "id": 25,
			 "entropy": 0.3063005102327365
		},
		{
			 "id": 26,
			 "entropy": 0.19699898681003733
		},
		{
			 "id": 27,
			 "entropy": 0.6779010029792619
		},
		{
			 "id": 28,
			 "entropy": 1.0
		},
		{
			 "id": 29,
			 "entropy": 0.6857191401822644
		},
		{
			 "id": 30,
			 "entropy": 0.7115490090896258
		},
		{
			 "id": 31,
			 "entropy": 0.5469614933770278
		},
		{
			 "id": 32,
			 "entropy": 0.14336477819290724
		},
		{
			 "id": 33,
			 "entropy": 0.0
		},
		{
			 "id": 34,
			 "entropy": 0.7613452385331912
		},
		{
			 "id": 35,
			 "entropy": 0.9158251926487019
		},
		{
			 "id": 36,
			 "entropy": 0.5082394630881835
		}
		 ]
	},	 {		 "2009": [
		{
			 "id": 0,
			 "entropy": 0.7452146301890654
		},
		{
			 "id": 1,
			 "entropy": 0.7452146301890654
		},
		{
			 "id": 2,
			 "entropy": 0.7688400950668425
		},
		{
			 "id": 3,
			 "entropy": 0.7971539503685551
		},
		{
			 "id": 4,
			 "entropy": 0.8297701133169081
		},
		{
			 "id": 5,
			 "entropy": 0.6910766937170041
		},
		{
			 "id": 6,
			 "entropy": 1.0
		},
		{
			 "id": 7,
			 "entropy": 0.5128101088260287
		},
		{
			 "id": 8,
			 "entropy": 0.20252587577228237
		},
		{
			 "id": 9,
			 "entropy": 0.3614187967396096
		},
		{
			 "id": 10,
			 "entropy": 0.5475920463770363
		},
		{
			 "id": 11,
			 "entropy": 0.5140060859054328
		},
		{
			 "id": 12,
			 "entropy": 0.47448976302178236
		},
		{
			 "id": 13,
			 "entropy": 0.2971458758416181
		},
		{
			 "id": 14,
			 "entropy": 0.2688124001948464
		},
		{
			 "id": 15,
			 "entropy": 0.39939801480820014
		},
		{
			 "id": 16,
			 "entropy": 0.08918528132934538
		},
		{
			 "id": 17,
			 "entropy": 0.0
		},
		{
			 "id": 18,
			 "entropy": 0.1406387965778258
		},
		{
			 "id": 19,
			 "entropy": 0.24042361075187357
		},
		{
			 "id": 20,
			 "entropy": 0.12021180537593679
		},
		{
			 "id": 21,
			 "entropy": 0.581415416289594
		},
		{
			 "id": 22,
			 "entropy": 0.3888833778819735
		},
		{
			 "id": 23,
			 "entropy": 0.24042361075187357
		},
		{
			 "id": 24,
			 "entropy": 0.5193455728851745
		},
		{
			 "id": 25,
			 "entropy": 0.08918528132934538
		},
		{
			 "id": 26,
			 "entropy": 0.20252587577228237
		},
		{
			 "id": 27,
			 "entropy": 0.34125293240832016
		},
		{
			 "id": 28,
			 "entropy": 0.4759566915080786
		},
		{
			 "id": 29,
			 "entropy": 0.46489768498379175
		},
		{
			 "id": 30,
			 "entropy": 0.42731998080536987
		},
		{
			 "id": 31,
			 "entropy": 0.5265032072901751
		},
		{
			 "id": 32,
			 "entropy": 0.36063541612781036
		},
		{
			 "id": 33,
			 "entropy": 0.30092120374574155
		},
		{
			 "id": 34,
			 "entropy": 0.43453079627126034
		},
		{
			 "id": 35,
			 "entropy": 0.24042361075187357
		},
		{
			 "id": 36,
			 "entropy": 0.43453079627126034
		}
		 ]
	},	 {		 "2008": [
		{
			 "id": 0,
			 "entropy": 1.0
		},
		{
			 "id": 1,
			 "entropy": 0.8013413042450866
		},
		{
			 "id": 2,
			 "entropy": 0.8471153086085721
		},
		{
			 "id": 3,
			 "entropy": 0.8408890251162248
		},
		{
			 "id": 4,
			 "entropy": 0.8291167511933576
		},
		{
			 "id": 5,
			 "entropy": 0.9970856736598189
		},
		{
			 "id": 6,
			 "entropy": 0.8516059336604305
		},
		{
			 "id": 7,
			 "entropy": 0.0
		},
		{
			 "id": 8,
			 "entropy": 0.1638265584265501
		},
		{
			 "id": 9,
			 "entropy": 0.32018192788679967
		},
		{
			 "id": 10,
			 "entropy": 0.3687202074435502
		},
		{
			 "id": 11,
			 "entropy": 0.2825378744551151
		},
		{
			 "id": 12,
			 "entropy": 0.3710480963834234
		},
		{
			 "id": 13,
			 "entropy": 0.10164168364727247
		},
		{
			 "id": 14,
			 "entropy": 0.30163816545952266
		},
		{
			 "id": 15,
			 "entropy": 0.0
		},
		{
			 "id": 16,
			 "entropy": 0.352455715923485
		},
		{
			 "id": 17,
			 "entropy": 0.37928239089763777
		},
		{
			 "id": 18,
			 "entropy": 0.3841350250987304
		},
		{
			 "id": 19,
			 "entropy": 0.3884927922710727
		},
		{
			 "id": 20,
			 "entropy": 0.46360748219869957
		},
		{
			 "id": 21,
			 "entropy": 0.0776442254381149
		},
		{
			 "id": 22,
			 "entropy": 0.3801812555716596
		},
		{
			 "id": 23,
			 "entropy": 0.45166262350657843
		},
		{
			 "id": 24,
			 "entropy": 0.10164168364727247
		},
		{
			 "id": 25,
			 "entropy": 0.0
		},
		{
			 "id": 26,
			 "entropy": 0.12519114987937843
		},
		{
			 "id": 27,
			 "entropy": 0.0
		},
		{
			 "id": 28,
			 "entropy": 0.4268293153389011
		},
		{
			 "id": 29,
			 "entropy": 0.10164168364727247
		},
		{
			 "id": 30,
			 "entropy": 0.41105447760421737
		},
		{
			 "id": 31,
			 "entropy": 0.3232361402339274
		},
		{
			 "id": 32,
			 "entropy": 0.18466204715554566
		},
		{
			 "id": 33,
			 "entropy": 0.19952666170299052
		},
		{
			 "id": 34,
			 "entropy": 0.4824999007759331
		},
		{
			 "id": 35,
			 "entropy": 0.13736930628495153
		},
		{
			 "id": 36,
			 "entropy": 0.48630021261506834
		}
		 ]
	},	 {		 "2007": [
		{
			 "id": 0,
			 "entropy": 0.9941177432881471
		},
		{
			 "id": 1,
			 "entropy": 0.8116821776082159
		},
		{
			 "id": 2,
			 "entropy": 0.9162653340586926
		},
		{
			 "id": 3,
			 "entropy": 0.9249656990039526
		},
		{
			 "id": 4,
			 "entropy": 0.854258241256579
		},
		{
			 "id": 5,
			 "entropy": 1.0
		},
		{
			 "id": 6,
			 "entropy": 0.8981970205984786
		},
		{
			 "id": 7,
			 "entropy": 0.42519177577406386
		},
		{
			 "id": 8,
			 "entropy": 0.3536414809992729
		},
		{
			 "id": 9,
			 "entropy": 0.3536414809992729
		},
		{
			 "id": 10,
			 "entropy": 0.6263852626641502
		},
		{
			 "id": 11,
			 "entropy": 0.5180754054914067
		},
		{
			 "id": 12,
			 "entropy": 0.5894024683321214
		},
		{
			 "id": 13,
			 "entropy": 0.6965737514590199
		},
		{
			 "id": 14,
			 "entropy": 0.33468439868927474
		},
		{
			 "id": 15,
			 "entropy": 0.42519177577406386
		},
		{
			 "id": 16,
			 "entropy": 0.33468439868927474
		},
		{
			 "id": 17,
			 "entropy": 0.628107211230948
		},
		{
			 "id": 18,
			 "entropy": 0.3536414809992729
		},
		{
			 "id": 19,
			 "entropy": 0.5537274330521694
		},
		{
			 "id": 20,
			 "entropy": 0.2231229324595165
		},
		{
			 "id": 21,
			 "entropy": 0.446245864919033
		},
		{
			 "id": 22,
			 "entropy": 0.0
		},
		{
			 "id": 23,
			 "entropy": 0.30589051689184305
		},
		{
			 "id": 24,
			 "entropy": 0.2231229324595165
		},
		{
			 "id": 25,
			 "entropy": 0.3536414809992729
		},
		{
			 "id": 26,
			 "entropy": 0.5307611487529287
		},
		{
			 "id": 27,
			 "entropy": 0.549522140114863
		},
		{
			 "id": 28,
			 "entropy": 0.6883465413262202
		},
		{
			 "id": 29,
			 "entropy": 0.5585343403588682
		},
		{
			 "id": 30,
			 "entropy": 0.6577000881186532
		},
		{
			 "id": 31,
			 "entropy": 0.5626999919833101
		},
		{
			 "id": 32,
			 "entropy": 0.446245864919033
		},
		{
			 "id": 33,
			 "entropy": 0.5023901026389506
		},
		{
			 "id": 34,
			 "entropy": 0.5935359511303405
		},
		{
			 "id": 35,
			 "entropy": 0.3536414809992729
		},
		{
			 "id": 36,
			 "entropy": 0.53957725804887
		}
		 ]
	},	 {		 "2013": [
		{
			 "id": 0,
			 "entropy": 1.0
		},
		{
			 "id": 1,
			 "entropy": 0.9025780361564957
		},
		{
			 "id": 2,
			 "entropy": 0.8890816067289811
		},
		{
			 "id": 3,
			 "entropy": 0.9003071532648691
		},
		{
			 "id": 4,
			 "entropy": 0.9831653468876732
		},
		{
			 "id": 5,
			 "entropy": 0.819399689772383
		},
		{
			 "id": 6,
			 "entropy": 0.8136929340781452
		},
		{
			 "id": 7,
			 "entropy": 0.35460384038785087
		},
		{
			 "id": 8,
			 "entropy": 0.44325480048481347
		},
		{
			 "id": 9,
			 "entropy": 0.4806259822844821
		},
		{
			 "id": 10,
			 "entropy": 0.32174698739988944
		},
		{
			 "id": 11,
			 "entropy": 0.17730192019392538
		},
		{
			 "id": 12,
			 "entropy": 0.33314714153851993
		},
		{
			 "id": 13,
			 "entropy": 0.021729458264973196
		},
		{
			 "id": 14,
			 "entropy": 0.40006864337050946
		},
		{
			 "id": 15,
			 "entropy": 0.4871469987740274
		},
		{
			 "id": 16,
			 "entropy": 0.46205143558703127
		},
		{
			 "id": 17,
			 "entropy": 0.2876823385558613
		},
		{
			 "id": 18,
			 "entropy": 0.2876823385558613
		},
		{
			 "id": 19,
			 "entropy": 0.17730192019392538
		},
		{
			 "id": 20,
			 "entropy": 0.0
		},
		{
			 "id": 21,
			 "entropy": 0.2876823385558613
		},
		{
			 "id": 22,
			 "entropy": 0.3733000426377136
		},
		{
			 "id": 23,
			 "entropy": 0.2876823385558613
		},
		{
			 "id": 24,
			 "entropy": 0.2876823385558613
		},
		{
			 "id": 25,
			 "entropy": 0.5024007054941068
		},
		{
			 "id": 26,
			 "entropy": 0.021729458264973196
		},
		{
			 "id": 27,
			 "entropy": 0.27995656548034237
		},
		{
			 "id": 28,
			 "entropy": 0.17730192019392538
		},
		{
			 "id": 29,
			 "entropy": 0.39714913396034324
		},
		{
			 "id": 30,
			 "entropy": 0.42065877870130536
		},
		{
			 "id": 31,
			 "entropy": 0.5024007054941068
		},
		{
			 "id": 32,
			 "entropy": 0.4194893636021776
		},
		{
			 "id": 33,
			 "entropy": 0.19845455659023456
		},
		{
			 "id": 34,
			 "entropy": 0.34011753487786867
		},
		{
			 "id": 35,
			 "entropy": 0.2876823385558613
		},
		{
			 "id": 36,
			 "entropy": 0.5039372597260495
		}
		 ]
	},	 {		 "2012": [
		{
			 "id": 0,
			 "entropy": 0.9542336992527876
		},
		{
			 "id": 1,
			 "entropy": 0.8082039600430688
		},
		{
			 "id": 2,
			 "entropy": 0.8273521062105295
		},
		{
			 "id": 3,
			 "entropy": 0.7364746053090873
		},
		{
			 "id": 4,
			 "entropy": 0.8869373895861021
		},
		{
			 "id": 5,
			 "entropy": 1.0
		},
		{
			 "id": 6,
			 "entropy": 0.9267495106832575
		},
		{
			 "id": 7,
			 "entropy": 0.22161399863010783
		},
		{
			 "id": 8,
			 "entropy": 0.5248977482153384
		},
		{
			 "id": 9,
			 "entropy": 0.44322799726021567
		},
		{
			 "id": 10,
			 "entropy": 0.554757089173776
		},
		{
			 "id": 11,
			 "entropy": 0.3324209979451618
		},
		{
			 "id": 12,
			 "entropy": 0.3512498774635906
		},
		{
			 "id": 13,
			 "entropy": 0.4259261701875337
		},
		{
			 "id": 14,
			 "entropy": 0.46939578138528776
		},
		{
			 "id": 15,
			 "entropy": 0.3512498774635906
		},
		{
			 "id": 16,
			 "entropy": 0.4190856147003191
		},
		{
			 "id": 17,
			 "entropy": 0.22161399863010783
		},
		{
			 "id": 18,
			 "entropy": 0.3324209979451618
		},
		{
			 "id": 19,
			 "entropy": 0.22161399863010783
		},
		{
			 "id": 20,
			 "entropy": 0.0
		},
		{
			 "id": 21,
			 "entropy": 0.22161399863010783
		},
		{
			 "id": 22,
			 "entropy": 0.3512498774635906
		},
		{
			 "id": 23,
			 "entropy": 0.49551257920532443
		},
		{
			 "id": 24,
			 "entropy": 0.40829520275810216
		},
		{
			 "id": 25,
			 "entropy": 0.3512498774635906
		},
		{
			 "id": 26,
			 "entropy": 0.44322799726021567
		},
		{
			 "id": 27,
			 "entropy": 0.5972012949143631
		},
		{
			 "id": 28,
			 "entropy": 0.49899254321699577
		},
		{
			 "id": 29,
			 "entropy": 0.6094384962327966
		},
		{
			 "id": 30,
			 "entropy": 0.49899254321699577
		},
		{
			 "id": 31,
			 "entropy": 0.6839115729415878
		},
		{
			 "id": 32,
			 "entropy": 0.44322799726021567
		},
		{
			 "id": 33,
			 "entropy": 0.3324209979451618
		},
		{
			 "id": 34,
			 "entropy": 0.3512498774635906
		},
		{
			 "id": 35,
			 "entropy": 0.3512498774635906
		},
		{
			 "id": 36,
			 "entropy": 0.3324209979451618
		}
		 ]
	},	 {		 "2011": [
		{
			 "id": 0,
			 "entropy": 1.0
		},
		{
			 "id": 1,
			 "entropy": 0.8008622085632658
		},
		{
			 "id": 2,
			 "entropy": 0.7959457681334128
		},
		{
			 "id": 3,
			 "entropy": 0.7789771506499767
		},
		{
			 "id": 4,
			 "entropy": 0.9146677340467843
		},
		{
			 "id": 5,
			 "entropy": 0.8595916831448746
		},
		{
			 "id": 6,
			 "entropy": 0.9440694453333707
		},
		{
			 "id": 7,
			 "entropy": 0.3333906596056234
		},
		{
			 "id": 8,
			 "entropy": 0.21034608670800164
		},
		{
			 "id": 9,
			 "entropy": 0.21034608670800164
		},
		{
			 "id": 10,
			 "entropy": 0.4206921734160033
		},
		{
			 "id": 11,
			 "entropy": 0.3333906596056234
		},
		{
			 "id": 12,
			 "entropy": 0.0
		},
		{
			 "id": 13,
			 "entropy": 0.4206921734160033
		},
		{
			 "id": 14,
			 "entropy": 0.3333906596056234
		},
		{
			 "id": 15,
			 "entropy": 0.4206921734160033
		},
		{
			 "id": 16,
			 "entropy": 0.6987545750849238
		},
		{
			 "id": 17,
			 "entropy": 0.21034608670800164
		},
		{
			 "id": 18,
			 "entropy": 0.4206921734160033
		},
		{
			 "id": 19,
			 "entropy": 0.3333906596056234
		},
		{
			 "id": 20,
			 "entropy": 0.4206921734160033
		},
		{
			 "id": 21,
			 "entropy": 0.543736746313625
		},
		{
			 "id": 22,
			 "entropy": 0.3333906596056234
		},
		{
			 "id": 23,
			 "entropy": 0.6310382601240049
		},
		{
			 "id": 24,
			 "entropy": 0.21034608670800164
		},
		{
			 "id": 25,
			 "entropy": 0.3333906596056234
		},
		{
			 "id": 26,
			 "entropy": 0.21034608670800164
		},
		{
			 "id": 27,
			 "entropy": 0.4206921734160033
		},
		{
			 "id": 28,
			 "entropy": 0.3333906596056234
		},
		{
			 "id": 29,
			 "entropy": 0.3333906596056234
		},
		{
			 "id": 30,
			 "entropy": 0.48840848837692213
		},
		{
			 "id": 31,
			 "entropy": 0.21034608670800164
		},
		{
			 "id": 32,
			 "entropy": 0.4206921734160033
		},
		{
			 "id": 33,
			 "entropy": 0.4206921734160033
		},
		{
			 "id": 34,
			 "entropy": 0.4206921734160033
		},
		{
			 "id": 35,
			 "entropy": 0.590516121855264
		},
		{
			 "id": 36,
			 "entropy": 0.7540828330216267
		}
		 ]
	},	 {		 "2010": [
		{
			 "id": 0,
			 "entropy": 1.0
		},
		{
			 "id": 1,
			 "entropy": 0.831467715666133
		},
		{
			 "id": 2,
			 "entropy": 0.645352257423052
		},
		{
			 "id": 3,
			 "entropy": 0.7549294053384749
		},
		{
			 "id": 4,
			 "entropy": 0.8682389764718187
		},
		{
			 "id": 5,
			 "entropy": 0.8048926198557677
		},
		{
			 "id": 6,
			 "entropy": 0.7479292902946655
		},
		{
			 "id": 7,
			 "entropy": 0.0
		},
		{
			 "id": 8,
			 "entropy": 0.6017839179645582
		},
		{
			 "id": 9,
			 "entropy": 0.0
		},
		{
			 "id": 10,
			 "entropy": 0.46822699194451906
		},
		{
			 "id": 11,
			 "entropy": 0.31961464512686827
		},
		{
			 "id": 12,
			 "entropy": 0.0
		},
		{
			 "id": 13,
			 "entropy": 0.3614617118511579
		},
		{
			 "id": 14,
			 "entropy": 0.2016543892877238
		},
		{
			 "id": 15,
			 "entropy": 0.0
		},
		{
			 "id": 16,
			 "entropy": 0.47969213262667293
		},
		{
			 "id": 17,
			 "entropy": 0.4776229638432474
		},
		{
			 "id": 18,
			 "entropy": 0.5336661098366376
		},
		{
			 "id": 19,
			 "entropy": 0.30690348051433997
		},
		{
			 "id": 20,
			 "entropy": 0.4033087785754476
		},
		{
			 "id": 21,
			 "entropy": 0.4976265897942256
		},
		{
			 "id": 22,
			 "entropy": 0.521269034414592
		},
		{
			 "id": 23,
			 "entropy": 0.3868327748894429
		},
		{
			 "id": 24,
			 "entropy": 0.31961464512686827
		},
		{
			 "id": 25,
			 "entropy": 0.31961464512686827
		},
		{
			 "id": 26,
			 "entropy": 0.5371130710179006
		},
		{
			 "id": 27,
			 "entropy": 0.38756523622942957
		},
		{
			 "id": 28,
			 "entropy": 0.2016543892877238
		},
		{
			 "id": 29,
			 "entropy": 0.0
		},
		{
			 "id": 30,
			 "entropy": 0.4958979713763071
		},
		{
			 "id": 31,
			 "entropy": 0.42913773726703963
		},
		{
			 "id": 32,
			 "entropy": 0.46822699194451906
		},
		{
			 "id": 33,
			 "entropy": 0.31961464512686827
		},
		{
			 "id": 34,
			 "entropy": 0.2016543892877238
		},
		{
			 "id": 35,
			 "entropy": 0.2764582048683981
		},
		{
			 "id": 36,
			 "entropy": 0.2016543892877238
		}
		 ]
	}]